Hexadecimal_keypad/design.sv

//DESIGN BY : PRANESH S

module Hex_Keypad_Grayhill_072(
    input [3:0] Row,
    input S_Row,
    input clock,
    input reset,
    output reg [3:0] Code,
    output Valid,
    output reg [3:0] Col
    );
    
    reg [5: 0] state, next_state;
    
   // One-hot encoding
    parameter S_0 = 6'b000001, S_1 = 6'b000010, S_2 = 6'b000100;
    parameter S_3 = 6'b001000, S_4 = 6'b010000, S_5 = 6'b100000;
    assign Valid = ((state == S_1) || (state == S_2) || (state == S_3) || (state == S_4)) && Row;
    always @ (Row or Col)
    case ({Row, Col})
        8'b0001_0001: Code = 0; 
        8'b0001_0010: Code = 1;
        8'b0001_0100: Code = 2; 
        8'b0001_1000: Code = 3;
        8'b0010_0001: Code = 4; 
        8'b0010_0010: Code = 5;
        8'b0010_0100: Code = 6;
        8'b0010_1000: Code = 7;
        8'b0100_0001: Code = 8;
        8'b0100_0010: Code = 9;
        8'b0100_0100: Code = 10;        //A
        8'b0100_1000: Code = 11;        //B
        8'b1000_0001: Code = 12;        //C
        8'b1000_0010: Code = 13;        //D
        8'b1000_0100: Code = 14;        //E
        8'b1000_1000: Code = 15;        //F
        default: Code = 0;                     //Arbitrary choice
    endcase
    always @(posedge clock or posedge reset)
    if (reset) state <= S_0;
    else state <= next_state;
    always@ (state or S_Row or Row)                 // Next-state logic
    begin next_state = state; Col = 0;
    case (state)
        //Assert all columns
        S_0: begin Col = 15; if (S_Row) next_state =S_1; end
        //Assert column 0
        S_1: begin Col = 1; if (Row) next_state = S_5; else next_state = S_2; end
        //Assert column 1
        S_2: begin Col = 2; if (Row) next_state = S_5; else next_state = S_3; end
        // Assert column 2
        S_3: begin Col = 4; if (Row) next_state = S_5; else next_state= S_4; end
       // Assert column 3
        S_4: begin Col = 8; if (Row) next_state = S_5; else next_state = S_0; end
        // Assert all rows
        S_5: begin Col = 15; if (Row ==0) next_state = S_0; end
    endcase
    end
endmodule


module Row_Signal(                                                //Scans for row of the asserted key
    input [15:0] Key,
    input [3:0] Col,
    output reg [3:0] Row
    );
    
    always @(Key or Col) begin                                  //Combinational logic for key assertion
    Row[0] =  Key[0] && Col[0] || Key[1] && Col[1] || Key[2] && Col[2] || Key[3] && Col[3];
    Row[1] =  Key[4] && Col[0] || Key[5] && Col[1] || Key[6] && Col[2] || Key[7] && Col[3];
    Row[2] =  Key[8] && Col[0] || Key[9] && Col[1] || Key[10] && Col[2] || Key[11] && Col[3];
    Row[3] =  Key[12] && Col[0] || Key[13] && Col[1] || Key[14] && Col[2] || Key[15] && Col[3];
    end

endmodule

module Synchronizer(
    input [3:0] Row,
    input clock,
    input reset,
    output reg S_Row
    );
    reg A_Row;
    
    always @ (negedge clock or posedge reset)
    begin
    if (reset) 
    begin 
    A_Row <= 0;
    S_Row <= 0;
    end
    else 
    begin 
    A_Row <= (Row[0] || Row[1] || Row[2] || Row[3]);
    S_Row <= A_Row;
    end 
    end
        
endmodule

Hexadecimal_keypad/testbench.sv
`timescale 1ns / 1ps

module test_Hex_Keypad ();
    wire [3:0] Code;
    wire Valid;
    wire [3:0] Col;
    wire [3:0] Row;
    reg clock, reset;
    reg [15:0] Key;
    reg [39:0] Pressed;
    
    // Key name parameters
    parameter [39:0] Key_0 = "Key_0";
    parameter [39:0] Key_1 = "Key_1";
    parameter [39:0] Key_2 = "Key_2";
    parameter [39:0] Key_3 = "Key_3";
    parameter [39:0] Key_4 = "Key_4";
    parameter [39:0] Key_5 = "Key_5";
    parameter [39:0] Key_6 = "Key_6";
    parameter [39:0] Key_7 = "Key_7";
    parameter [39:0] Key_8 = "Key_8";
    parameter [39:0] Key_9 = "Key_9";
    parameter [39:0] Key_A = "Key_A"; 
    parameter [39:0] Key_B = "Key_B";
    parameter [39:0] Key_C = "Key_C"; 
    parameter [39:0] Key_D = "Key_D"; 
    parameter [39:0] Key_E = "Key_E";
    parameter [39:0] Key_F = "Key_F";
    parameter [39:0] None = "None";
    
    integer j, k;
    
    // Key press decoder
    always @(Key) begin
        case (Key)
            16'h0000: Pressed = None;
            16'h0001: Pressed = Key_0;
            16'h0002: Pressed = Key_1;
            16'h0004: Pressed = Key_2;
            16'h0008: Pressed = Key_3;
            16'h0010: Pressed = Key_4;
            16'h0020: Pressed = Key_5;
            16'h0040: Pressed = Key_6;
            16'h0080: Pressed = Key_7;
            16'h0100: Pressed = Key_8;
            16'h0200: Pressed = Key_9;
            16'h0400: Pressed = Key_A;
            16'h0800: Pressed = Key_B;
            16'h1000: Pressed = Key_C;
            16'h2000: Pressed = Key_D;
            16'h4000: Pressed = Key_E;
            16'h8000: Pressed = Key_F;
            default: Pressed = None;
        endcase
    end
    
    // Module instantiations
    Hex_Keypad_Grayhill_072 M1(Row, S_Row, clock, reset, Code, Valid, Col);
    Row_Signal M2(Key, Col, Row);
    Synchronizer M3(Row, clock, reset, S_Row);
    
    // VCD Dump setup
    initial begin
        $dumpfile("hex_keypad_waveform.vcd");  // Waveform output file
        $dumpvars(0, test_Hex_Keypad);        // Dump all variables
    end
    
    // Simulation control
    initial #2000 $finish;
    initial begin clock = 0; forever #5 clock = ~clock; end
    initial begin reset = 1; #10 reset = 0; end
    
    // Test sequence
    initial begin
        for (k = 0; k <= 1; k = k+1) begin 
            Key = 0;
            #20;
            for (j = 0; j <= 15; j = j+1) begin
                #20 Key = (1 << j);  // One-hot encoding
                #60 Key = 0;         // Release key
            end 
        end 
    end
endmodule

Hexadecimal_keypad/hex_keypad_waveform.vcd
$date
Wed Jun 25 11:51:12 2025
$end
$version
Riviera-PRO Version 2023.04.112.8911
$end
$timescale
1 ps
$end

$scope module test_Hex_Keypad $end
$var wire 4 ! Code [3:0] $end
$var wire 1 " Valid $end
$var wire 4 # Col [3:0] $end
$var wire 4 $ Row [3:0] $end
$var wire 1 % S_Row $end
$var reg 1 & clock $end
$var reg 1 ' reset $end
$var reg 16 ( Key [15:0] $end
$var reg 40 ) Pressed [39:0] $end
$var integer 32 * j $end
$var integer 32 + k $end
$var parameter 40 , Key_0 [39:0] $end
$var parameter 40 - Key_1 [39:0] $end
$var parameter 40 . Key_2 [39:0] $end
$var parameter 40 / Key_3 [39:0] $end
$var parameter 40 0 Key_4 [39:0] $end
$var parameter 40 1 Key_5 [39:0] $end
$var parameter 40 2 Key_6 [39:0] $end
$var parameter 40 3 Key_7 [39:0] $end
$var parameter 40 4 Key_8 [39:0] $end
$var parameter 40 5 Key_9 [39:0] $end
$var parameter 40 6 Key_A [39:0] $end
$var parameter 40 7 Key_B [39:0] $end
$var parameter 40 8 Key_C [39:0] $end
$var parameter 40 9 Key_D [39:0] $end
$var parameter 40 : Key_E [39:0] $end
$var parameter 40 ; Key_F [39:0] $end
$var parameter 40 < None [39:0] $end

$scope module M1 $end
$var wire 4 $ Row [3:0] $end
$var wire 1 % S_Row $end
$var wire 1 = clock $end
$var wire 1 > reset $end
$var wire 1 " Valid $end
$var reg 4 ? Code [3:0] $end
$var reg 4 @ Col [3:0] $end
$var reg 6 A state [5:0] $end
$var reg 6 B next_state [5:0] $end
$var parameter 6 C S_0 [5:0] $end
$var parameter 6 D S_1 [5:0] $end
$var parameter 6 E S_2 [5:0] $end
$var parameter 6 F S_3 [5:0] $end
$var parameter 6 G S_4 [5:0] $end
$var parameter 6 H S_5 [5:0] $end
$upscope $end


$scope module M2 $end
$var wire 16 I Key [15:0] $end
$var wire 4 # Col [3:0] $end
$var reg 4 J Row [3:0] $end
$upscope $end


$scope module M3 $end
$var wire 4 $ Row [3:0] $end
$var wire 1 = clock $end
$var wire 1 > reset $end
$var reg 1 K S_Row $end
$var reg 1 L A_Row $end
$upscope $end

$upscope $end

$enddefinitions $end
$dumpvars
b0 !
0"
b1111 #
b0 $
0%
0&
1'
b0 (
b1001110011011110110111001100101 )
bx *
b0 +
b100101101100101011110010101111100110000 ,
b100101101100101011110010101111100110001 -
b100101101100101011110010101111100110010 .
b100101101100101011110010101111100110011 /
b100101101100101011110010101111100110100 0
b100101101100101011110010101111100110101 1
b100101101100101011110010101111100110110 2
b100101101100101011110010101111100110111 3
b100101101100101011110010101111100111000 4
b100101101100101011110010101111100111001 5
b100101101100101011110010101111101000001 6
b100101101100101011110010101111101000010 7
b100101101100101011110010101111101000011 8
b100101101100101011110010101111101000100 9
b100101101100101011110010101111101000101 :
b100101101100101011110010101111101000110 ;
b1001110011011110110111001100101 <
0=
1>
b0 ?
b1111 @
b1 A
b1 B
b1 C
b10 D
b100 E
b1000 F
b10000 G
b100000 H
b0 I
b0 J
0K
0L
$end
#5000
1&
1=
#10000
0'
0&
0=
0>
#15000
1&
1=
#20000
b0 *
0&
0=
#25000
1&
1=
#30000
0&
0=
#35000
1&
1=
#40000
b1 (
0&
0=
b1 I
b100101101100101011110010101111100110000 )
b1 J
b1 $
b1111 @
#45000
1&
1=
#50000
0&
0=
1L
#55000
1&
1=
#60000
0&
0=
1K
1%
b1111 @
b10 B
#65000
1&
1=
b10 A
1"
b1 @
b100000 B
b1 #
#70000
0&
0=
#75000
1&
1=
b100000 A
0"
b1111 @
b1111 #
#80000
0&
0=
#85000
1&
1=
#90000
0&
0=
#95000
1&
1=
#100000
b0 (
b1 *
0&
0=
b0 I
b1001110011011110110111001100101 )
b0 J
b0 $
b1111 @
b1 B
#105000
1&
1=
b1 A
b1111 @
b10 B
#110000
0&
0=
0L
#115000
1&
1=
b10 A
b1 @
b100 B
b1 #
#120000
b10 (
0&
0=
b10 I
b100101101100101011110010101111100110001 )
0K
0%
b100 B
b1 @
#125000
1&
1=
b100 A
b10 @
b1000 B
b10 #
b1 J
b1 $
1"
b1 ?
b100000 B
b10 @
b1 !
#130000
0&
0=
1L
#135000
1&
1=
b100000 A
0"
b1111 @
b1111 #
b0 ?
b0 !
#140000
0&
0=
1K
1%
b1111 @
#145000
1&
1=
#150000
0&
0=
#155000
1&
1=
#160000
0&
0=
#165000
1&
1=
#170000
0&
0=
#175000
1&
1=
#180000
b0 (
b10 *
0&
0=
b0 I
b1001110011011110110111001100101 )
b0 J
b0 $
b1111 @
b1 B
#185000
1&
1=
b1 A
b1111 @
b10 B
#190000
0&
0=
0L
#195000
1&
1=
b10 A
b1 @
b100 B
b1 #
#200000
b100 (
0&
0=
b100 I
b100101101100101011110010101111100110010 )
0K
0%
b100 B
b1 @
#205000
1&
1=
b100 A
b10 @
b1000 B
b10 #
#210000
0&
0=
#215000
1&
1=
b1000 A
b100 @
b10000 B
b100 #
b1 J
b1 $
1"
b10 ?
b100000 B
b100 @
b10 !
#220000
0&
0=
1L
#225000
1&
1=
b100000 A
0"
b1111 @
b1111 #
b0 ?
b0 !
#230000
0&
0=
1K
1%
b1111 @
#235000
1&
1=
#240000
0&
0=
#245000
1&
1=
#250000
0&
0=
#255000
1&
1=
#260000
b0 (
b11 *
0&
0=
b0 I
b1001110011011110110111001100101 )
b0 J
b0 $
b1111 @
b1 B
#265000
1&
1=
b1 A
b1111 @
b10 B
#270000
0&
0=
0L
#275000
1&
1=
b10 A
b1 @
b100 B
b1 #
#280000
b1000 (
0&
0=
b1000 I
b100101101100101011110010101111100110011 )
0K
0%
b100 B
b1 @
#285000
1&
1=
b100 A
b10 @
b1000 B
b10 #
#290000
0&
0=
#295000
1&
1=
b1000 A
b100 @
b10000 B
b100 #
#300000
0&
0=
#305000
1&
1=
b10000 A
b1000 @
b1 B
b1000 #
b1 J
b1 $
1"
b11 ?
b100000 B
b1000 @
b11 !
#310000
0&
0=
1L
#315000
1&
1=
b100000 A
0"
b1111 @
b1111 #
b0 ?
b0 !
#320000
0&
0=
1K
1%
b1111 @
#325000
1&
1=
#330000
0&
0=
#335000
1&
1=
#340000
b0 (
b100 *
0&
0=
b0 I
b1001110011011110110111001100101 )
b0 J
b0 $
b1111 @
b1 B
#345000
1&
1=
b1 A
b1111 @
b10 B
#350000
0&
0=
0L
#355000
1&
1=
b10 A
b1 @
b100 B
b1 #
#360000
b10000 (
0&
0=
b10000 I
b100101101100101011110010101111100110100 )
b10 J
b10 $
1"
b100 ?
b100000 B
b1 @
b100 !
0K
0%
b100000 B
b1 @
#365000
1&
1=
b100000 A
0"
b1111 @
b1111 #
b0 ?
b0 !
#370000
0&
0=
1L
#375000
1&
1=
#380000
0&
0=
1K
1%
b1111 @
#385000
1&
1=
#390000
0&
0=
#395000
1&
1=
#400000
0&
0=
#405000
1&
1=
#410000
0&
0=
#415000
1&
1=
#420000
b0 (
b101 *
0&
0=
b0 I
b1001110011011110110111001100101 )
b0 J
b0 $
b1111 @
b1 B
#425000
1&
1=
b1 A
b1111 @
b10 B
#430000
0&
0=
0L
#435000
1&
1=
b10 A
b1 @
b100 B
b1 #
#440000
b100000 (
0&
0=
b100000 I
b100101101100101011110010101111100110101 )
0K
0%
b100 B
b1 @
#445000
1&
1=
b100 A
b10 @
b1000 B
b10 #
b10 J
b10 $
1"
b101 ?
b100000 B
b10 @
b101 !
#450000
0&
0=
1L
#455000
1&
1=
b100000 A
0"
b1111 @
b1111 #
b0 ?
b0 !
#460000
0&
0=
1K
1%
b1111 @
#465000
1&
1=
#470000
0&
0=
#475000
1&
1=
#480000
0&
0=
#485000
1&
1=
#490000
0&
0=
#495000
1&
1=
#500000
b0 (
b110 *
0&
0=
b0 I
b1001110011011110110111001100101 )
b0 J
b0 $
b1111 @
b1 B
#505000
1&
1=
b1 A
b1111 @
b10 B
#510000
0&
0=
0L
#515000
1&
1=
b10 A
b1 @
b100 B
b1 #
#520000
b1000000 (
0&
0=
b1000000 I
b100101101100101011110010101111100110110 )
0K
0%
b100 B
b1 @
#525000
1&
1=
b100 A
b10 @
b1000 B
b10 #
#530000
0&
0=
#535000
1&
1=
b1000 A
b100 @
b10000 B
b100 #
b10 J
b10 $
1"
b110 ?
b100000 B
b100 @
b110 !
#540000
0&
0=
1L
#545000
1&
1=
b100000 A
0"
b1111 @
b1111 #
b0 ?
b0 !
#550000
0&
0=
1K
1%
b1111 @
#555000
1&
1=
#560000
0&
0=
#565000
1&
1=
#570000
0&
0=
#575000
1&
1=
#580000
b0 (
b111 *
0&
0=
b0 I
b1001110011011110110111001100101 )
b0 J
b0 $
b1111 @
b1 B
#585000
1&
1=
b1 A
b1111 @
b10 B
#590000
0&
0=
0L
#595000
1&
1=
b10 A
b1 @
b100 B
b1 #
#600000
b10000000 (
0&
0=
b10000000 I
b100101101100101011110010101111100110111 )
0K
0%
b100 B
b1 @
#605000
1&
1=
b100 A
b10 @
b1000 B
b10 #
#610000
0&
0=
#615000
1&
1=
b1000 A
b100 @
b10000 B
b100 #
#620000
0&
0=
#625000
1&
1=
b10000 A
b1000 @
b1 B
b1000 #
b10 J
b10 $
1"
b111 ?
b100000 B
b1000 @
b111 !
#630000
0&
0=
1L
#635000
1&
1=
b100000 A
0"
b1111 @
b1111 #
b0 ?
b0 !
#640000
0&
0=
1K
1%
b1111 @
#645000
1&
1=
#650000
0&
0=
#655000
1&
1=
#660000
b0 (
b1000 *
0&
0=
b0 I
b1001110011011110110111001100101 )
b0 J
b0 $
b1111 @
b1 B
#665000
1&
1=
b1 A
b1111 @
b10 B
#670000
0&
0=
0L
#675000
1&
1=
b10 A
b1 @
b100 B
b1 #
#680000
b100000000 (
0&
0=
b100000000 I
b100101101100101011110010101111100111000 )
b100 J
b100 $
1"
b1000 ?
b100000 B
b1 @
b1000 !
0K
0%
b100000 B
b1 @
#685000
1&
1=
b100000 A
0"
b1111 @
b1111 #
b0 ?
b0 !
#690000
0&
0=
1L
#695000
1&
1=
#700000
0&
0=
1K
1%
b1111 @
#705000
1&
1=
#710000
0&
0=
#715000
1&
1=
#720000
0&
0=
#725000
1&
1=
#730000
0&
0=
#735000
1&
1=
#740000
b0 (
b1001 *
0&
0=
b0 I
b1001110011011110110111001100101 )
b0 J
b0 $
b1111 @
b1 B
#745000
1&
1=
b1 A
b1111 @
b10 B
#750000
0&
0=
0L
#755000
1&
1=
b10 A
b1 @
b100 B
b1 #
#760000
b1000000000 (
0&
0=
b1000000000 I
b100101101100101011110010101111100111001 )
0K
0%
b100 B
b1 @
#765000
1&
1=
b100 A
b10 @
b1000 B
b10 #
b100 J
b100 $
1"
b1001 ?
b100000 B
b10 @
b1001 !
#770000
0&
0=
1L
#775000
1&
1=
b100000 A
0"
b1111 @
b1111 #
b0 ?
b0 !
#780000
0&
0=
1K
1%
b1111 @
#785000
1&
1=
#790000
0&
0=
#795000
1&
1=
#800000
0&
0=
#805000
1&
1=
#810000
0&
0=
#815000
1&
1=
#820000
b0 (
b1010 *
0&
0=
b0 I
b1001110011011110110111001100101 )
b0 J
b0 $
b1111 @
b1 B
#825000
1&
1=
b1 A
b1111 @
b10 B
#830000
0&
0=
0L
#835000
1&
1=
b10 A
b1 @
b100 B
b1 #
#840000
b10000000000 (
0&
0=
b10000000000 I
b100101101100101011110010101111101000001 )
0K
0%
b100 B
b1 @
#845000
1&
1=
b100 A
b10 @
b1000 B
b10 #
#850000
0&
0=
#855000
1&
1=
b1000 A
b100 @
b10000 B
b100 #
b100 J
b100 $
1"
b1010 ?
b100000 B
b100 @
b1010 !
#860000
0&
0=
1L
#865000
1&
1=
b100000 A
0"
b1111 @
b1111 #
b0 ?
b0 !
#870000
0&
0=
1K
1%
b1111 @
#875000
1&
1=
#880000
0&
0=
#885000
1&
1=
#890000
0&
0=
#895000
1&
1=
#900000
b0 (
b1011 *
0&
0=
b0 I
b1001110011011110110111001100101 )
b0 J
b0 $
b1111 @
b1 B
#905000
1&
1=
b1 A
b1111 @
b10 B
#910000
0&
0=
0L
#915000
1&
1=
b10 A
b1 @
b100 B
b1 #
#920000
b100000000000 (
0&
0=
b100000000000 I
b100101101100101011110010101111101000010 )
0K
0%
b100 B
b1 @
#925000
1&
1=
b100 A
b10 @
b1000 B
b10 #
#930000
0&
0=
#935000
1&
1=
b1000 A
b100 @
b10000 B
b100 #
#940000
0&
0=
#945000
1&
1=
b10000 A
b1000 @
b1 B
b1000 #
b100 J
b100 $
1"
b1011 ?
b100000 B
b1000 @
b1011 !
#950000
0&
0=
1L
#955000
1&
1=
b100000 A
0"
b1111 @
b1111 #
b0 ?
b0 !
#960000
0&
0=
1K
1%
b1111 @
#965000
1&
1=
#970000
0&
0=
#975000
1&
1=
#980000
b0 (
b1100 *
0&
0=
b0 I
b1001110011011110110111001100101 )
b0 J
b0 $
b1111 @
b1 B
#985000
1&
1=
b1 A
b1111 @
b10 B
#990000
0&
0=
0L
#995000
1&
1=
b10 A
b1 @
b100 B
b1 #
#1000000
b1000000000000 (
0&
0=
b1000000000000 I
b100101101100101011110010101111101000011 )
b1000 J
b1000 $
1"
b1100 ?
b100000 B
b1 @
b1100 !
0K
0%
b100000 B
b1 @
#1005000
1&
1=
b100000 A
0"
b1111 @
b1111 #
b0 ?
b0 !
#1010000
0&
0=
1L
#1015000
1&
1=
#1020000
0&
0=
1K
1%
b1111 @
#1025000
1&
1=
#1030000
0&
0=
#1035000
1&
1=
#1040000
0&
0=
#1045000
1&
1=
#1050000
0&
0=
#1055000
1&
1=
#1060000
b0 (
b1101 *
0&
0=
b0 I
b1001110011011110110111001100101 )
b0 J
b0 $
b1111 @
b1 B
#1065000
1&
1=
b1 A
b1111 @
b10 B
#1070000
0&
0=
0L
#1075000
1&
1=
b10 A
b1 @
b100 B
b1 #
#1080000
b10000000000000 (
0&
0=
b10000000000000 I
b100101101100101011110010101111101000100 )
0K
0%
b100 B
b1 @
#1085000
1&
1=
b100 A
b10 @
b1000 B
b10 #
b1000 J
b1000 $
1"
b1101 ?
b100000 B
b10 @
b1101 !
#1090000
0&
0=
1L
#1095000
1&
1=
b100000 A
0"
b1111 @
b1111 #
b0 ?
b0 !
#1100000
0&
0=
1K
1%
b1111 @
#1105000
1&
1=
#1110000
0&
0=
#1115000
1&
1=
#1120000
0&
0=
#1125000
1&
1=
#1130000
0&
0=
#1135000
1&
1=
#1140000
b0 (
b1110 *
0&
0=
b0 I
b1001110011011110110111001100101 )
b0 J
b0 $
b1111 @
b1 B
#1145000
1&
1=
b1 A
b1111 @
b10 B
#1150000
0&
0=
0L
#1155000
1&
1=
b10 A
b1 @
b100 B
b1 #
#1160000
b100000000000000 (
0&
0=
b100000000000000 I
b100101101100101011110010101111101000101 )
0K
0%
b100 B
b1 @
#1165000
1&
1=
b100 A
b10 @
b1000 B
b10 #
#1170000
0&
0=
#1175000
1&
1=
b1000 A
b100 @
b10000 B
b100 #
b1000 J
b1000 $
1"
b1110 ?
b100000 B
b100 @
b1110 !
#1180000
0&
0=
1L
#1185000
1&
1=
b100000 A
0"
b1111 @
b1111 #
b0 ?
b0 !
#1190000
0&
0=
1K
1%
b1111 @
#1195000
1&
1=
#1200000
0&
0=
#1205000
1&
1=
#1210000
0&
0=
#1215000
1&
1=
#1220000
b0 (
b1111 *
0&
0=
b0 I
b1001110011011110110111001100101 )
b0 J
b0 $
b1111 @
b1 B
#1225000
1&
1=
b1 A
b1111 @
b10 B
#1230000
0&
0=
0L
#1235000
1&
1=
b10 A
b1 @
b100 B
b1 #
#1240000
b1000000000000000 (
0&
0=
b1000000000000000 I
b100101101100101011110010101111101000110 )
0K
0%
b100 B
b1 @
#1245000
1&
1=
b100 A
b10 @
b1000 B
b10 #
#1250000
0&
0=
#1255000
1&
1=
b1000 A
b100 @
b10000 B
b100 #
#1260000
0&
0=
#1265000
1&
1=
b10000 A
b1000 @
b1 B
b1000 #
b1000 J
b1000 $
1"
b1111 ?
b100000 B
b1000 @
b1111 !
#1270000
0&
0=
1L
#1275000
1&
1=
b100000 A
0"
b1111 @
b1111 #
b0 ?
b0 !
#1280000
0&
0=
1K
1%
b1111 @
#1285000
1&
1=
#1290000
0&
0=
#1295000
1&
1=
#1300000
b0 (
b10000 *
b1 +
0&
0=
b0 I
b1001110011011110110111001100101 )
b0 J
b0 $
b1111 @
b1 B
#1305000
1&
1=
b1 A
b1111 @
b10 B
#1310000
0&
0=
0L
#1315000
1&
1=
b10 A
b1 @
b100 B
b1 #
#1320000
b0 *
0&
0=
0K
0%
b100 B
b1 @
#1325000
1&
1=
b100 A
b10 @
b1000 B
b10 #
#1330000
0&
0=
#1335000
1&
1=
b1000 A
b100 @
b10000 B
b100 #
#1340000
b1 (
0&
0=
b1 I
b100101101100101011110010101111100110000 )
#1345000
1&
1=
b10000 A
b1000 @
b1 B
b1000 #
#1350000
0&
0=
#1355000
1&
1=
b1 A
b1111 @
b1111 #
b1 J
b1 $
b1111 @
#1360000
0&
0=
1L
#1365000
1&
1=
#1370000
0&
0=
1K
1%
b1111 @
b10 B
#1375000
1&
1=
b10 A
1"
b1 @
b100000 B
b1 #
#1380000
0&
0=
#1385000
1&
1=
b100000 A
0"
b1111 @
b1111 #
#1390000
0&
0=
#1395000
1&
1=
#1400000
b0 (
b1 *
0&
0=
b0 I
b1001110011011110110111001100101 )
b0 J
b0 $
b1111 @
b1 B
#1405000
1&
1=
b1 A
b1111 @
b10 B
#1410000
0&
0=
0L
#1415000
1&
1=
b10 A
b1 @
b100 B
b1 #
#1420000
b10 (
0&
0=
b10 I
b100101101100101011110010101111100110001 )
0K
0%
b100 B
b1 @
#1425000
1&
1=
b100 A
b10 @
b1000 B
b10 #
b1 J
b1 $
1"
b1 ?
b100000 B
b10 @
b1 !
#1430000
0&
0=
1L
#1435000
1&
1=
b100000 A
0"
b1111 @
b1111 #
b0 ?
b0 !
#1440000
0&
0=
1K
1%
b1111 @
#1445000
1&
1=
#1450000
0&
0=
#1455000
1&
1=
#1460000
0&
0=
#1465000
1&
1=
#1470000
0&
0=
#1475000
1&
1=
#1480000
b0 (
b10 *
0&
0=
b0 I
b1001110011011110110111001100101 )
b0 J
b0 $
b1111 @
b1 B
#1485000
1&
1=
b1 A
b1111 @
b10 B
#1490000
0&
0=
0L
#1495000
1&
1=
b10 A
b1 @
b100 B
b1 #
#1500000
b100 (
0&
0=
b100 I
b100101101100101011110010101111100110010 )
0K
0%
b100 B
b1 @
#1505000
1&
1=
b100 A
b10 @
b1000 B
b10 #
#1510000
0&
0=
#1515000
1&
1=
b1000 A
b100 @
b10000 B
b100 #
b1 J
b1 $
1"
b10 ?
b100000 B
b100 @
b10 !
#1520000
0&
0=
1L
#1525000
1&
1=
b100000 A
0"
b1111 @
b1111 #
b0 ?
b0 !
#1530000
0&
0=
1K
1%
b1111 @
#1535000
1&
1=
#1540000
0&
0=
#1545000
1&
1=
#1550000
0&
0=
#1555000
1&
1=
#1560000
b0 (
b11 *
0&
0=
b0 I
b1001110011011110110111001100101 )
b0 J
b0 $
b1111 @
b1 B
#1565000
1&
1=
b1 A
b1111 @
b10 B
#1570000
0&
0=
0L
#1575000
1&
1=
b10 A
b1 @
b100 B
b1 #
#1580000
b1000 (
0&
0=
b1000 I
b100101101100101011110010101111100110011 )
0K
0%
b100 B
b1 @
#1585000
1&
1=
b100 A
b10 @
b1000 B
b10 #
#1590000
0&
0=
#1595000
1&
1=
b1000 A
b100 @
b10000 B
b100 #
#1600000
0&
0=
#1605000
1&
1=
b10000 A
b1000 @
b1 B
b1000 #
b1 J
b1 $
1"
b11 ?
b100000 B
b1000 @
b11 !
#1610000
0&
0=
1L
#1615000
1&
1=
b100000 A
0"
b1111 @
b1111 #
b0 ?
b0 !
#1620000
0&
0=
1K
1%
b1111 @
#1625000
1&
1=
#1630000
0&
0=
#1635000
1&
1=
#1640000
b0 (
b100 *
0&
0=
b0 I
b1001110011011110110111001100101 )
b0 J
b0 $
b1111 @
b1 B
#1645000
1&
1=
b1 A
b1111 @
b10 B
#1650000
0&
0=
0L
#1655000
1&
1=
b10 A
b1 @
b100 B
b1 #
#1660000
b10000 (
0&
0=
b10000 I
b100101101100101011110010101111100110100 )
b10 J
b10 $
1"
b100 ?
b100000 B
b1 @
b100 !
0K
0%
b100000 B
b1 @
#1665000
1&
1=
b100000 A
0"
b1111 @
b1111 #
b0 ?
b0 !
#1670000
0&
0=
1L
#1675000
1&
1=
#1680000
0&
0=
1K
1%
b1111 @
#1685000
1&
1=
#1690000
0&
0=
#1695000
1&
1=
#1700000
0&
0=
#1705000
1&
1=
#1710000
0&
0=
#1715000
1&
1=
#1720000
b0 (
b101 *
0&
0=
b0 I
b1001110011011110110111001100101 )
b0 J
b0 $
b1111 @
b1 B
#1725000
1&
1=
b1 A
b1111 @
b10 B
#1730000
0&
0=
0L
#1735000
1&
1=
b10 A
b1 @
b100 B
b1 #
#1740000
b100000 (
0&
0=
b100000 I
b100101101100101011110010101111100110101 )
0K
0%
b100 B
b1 @
#1745000
1&
1=
b100 A
b10 @
b1000 B
b10 #
b10 J
b10 $
1"
b101 ?
b100000 B
b10 @
b101 !
#1750000
0&
0=
1L
#1755000
1&
1=
b100000 A
0"
b1111 @
b1111 #
b0 ?
b0 !
#1760000
0&
0=
1K
1%
b1111 @
#1765000
1&
1=
#1770000
0&
0=
#1775000
1&
1=
#1780000
0&
0=
#1785000
1&
1=
#1790000
0&
0=
#1795000
1&
1=
#1800000
b0 (
b110 *
0&
0=
b0 I
b1001110011011110110111001100101 )
b0 J
b0 $
b1111 @
b1 B
#1805000
1&
1=
b1 A
b1111 @
b10 B
#1810000
0&
0=
0L
#1815000
1&
1=
b10 A
b1 @
b100 B
b1 #
#1820000
b1000000 (
0&
0=
b1000000 I
b100101101100101011110010101111100110110 )
0K
0%
b100 B
b1 @
#1825000
1&
1=
b100 A
b10 @
b1000 B
b10 #
#1830000
0&
0=
#1835000
1&
1=
b1000 A
b100 @
b10000 B
b100 #
b10 J
b10 $
1"
b110 ?
b100000 B
b100 @
b110 !
#1840000
0&
0=
1L
#1845000
1&
1=
b100000 A
0"
b1111 @
b1111 #
b0 ?
b0 !
#1850000
0&
0=
1K
1%
b1111 @
#1855000
1&
1=
#1860000
0&
0=
#1865000
1&
1=
#1870000
0&
0=
#1875000
1&
1=
#1880000
b0 (
b111 *
0&
0=
b0 I
b1001110011011110110111001100101 )
b0 J
b0 $
b1111 @
b1 B
#1885000
1&
1=
b1 A
b1111 @
b10 B
#1890000
0&
0=
0L
#1895000
1&
1=
b10 A
b1 @
b100 B
b1 #
#1900000
b10000000 (
0&
0=
b10000000 I
b100101101100101011110010101111100110111 )
0K
0%
b100 B
b1 @
#1905000
1&
1=
b100 A
b10 @
b1000 B
b10 #
#1910000
0&
0=
#1915000
1&
1=
b1000 A
b100 @
b10000 B
b100 #
#1920000
0&
0=
#1925000
1&
1=
b10000 A
b1000 @
b1 B
b1000 #
b10 J
b10 $
1"
b111 ?
b100000 B
b1000 @
b111 !
#1930000
0&
0=
1L
#1935000
1&
1=
b100000 A
0"
b1111 @
b1111 #
b0 ?
b0 !
#1940000
0&
0=
1K
1%
b1111 @
#1945000
1&
1=
#1950000
0&
0=
#1955000
1&
1=
#1960000
b0 (
b1000 *
0&
0=
b0 I
b1001110011011110110111001100101 )
b0 J
b0 $
b1111 @
b1 B
#1965000
1&
1=
b1 A
b1111 @
b10 B
#1970000
0&
0=
0L
#1975000
1&
1=
b10 A
b1 @
b100 B
b1 #
#1980000
b100000000 (
0&
0=
b100000000 I
b100101101100101011110010101111100111000 )
b100 J
b100 $
1"
b1000 ?
b100000 B
b1 @
b1000 !
0K
0%
b100000 B
b1 @
#1985000
1&
1=
b100000 A
0"
b1111 @
b1111 #
b0 ?
b0 !
#1990000
0&
0=
1L
