voting machine/design.sv
//voting machine 
//Pranesh S
//VIT UNIVERSITY , VELLORE
//file name : voting machine

module voting_machine #(
parameter idle =  2'b00,					// states and their corresponding numbers
parameter vote =  2'b01,
parameter hold =  2'b10,
parameter finish = 2'b11
)(
    input clk,							
    input rst,							// input High to reset counting  (active high)
    input i_candidate_1,				// input to vote for candidate 1
    input i_candidate_2,				// input to vote for candidate 2
    input i_candidate_3,				// input to vote for candidate 3
    input i_voting_over,				// input high to get total votes after voting is over

    output reg [31:0] o_count1,			// output for total number of votes of candidate 1
    output reg [31:0] o_count2,			// output for total number of votes of candidate 2
    output reg [31:0] o_count3			// output for total number of votes of candidate 3

);	  

reg [31:0] r_cand1_prev;					// store previous value of input for candidate 1
reg [31:0] r_cand2_prev;					// store previous value of input for candidate 2
reg [31:0] r_cand3_prev;					// store previous value of input for candidate 3

reg [31:0] r_counter_1;						// counting register for candidate 1
reg [31:0] r_counter_2;						// counting register for candidate 2
reg [31:0] r_counter_3;						// counting register for candidate 3

reg [1:0] r_present_state, r_next_state;		// present state and next state registers
//reg [1:0] r_state_no;					     // store state number
reg [3:0] r_hold_count;                        //counter for hold state

//////////// always block that assigns next state & internal reg operations /////////////////////////////////// 
always @(posedge clk or negedge rst)
	begin
		case (r_present_state)														

			idle: if (!rst)												// idle state operations
						begin
							r_next_state <= vote;									// assign next state vote when reset low
							//r_state_no <= 2'b01;
						end	

					else
						begin
						//r_present_state = idle;									// present state at the beginning
							r_counter_1 <= 32'b0;										// clear counting registers
							r_counter_2 <= 32'b0;
							r_counter_3 <= 32'b0;
							r_hold_count <= 4'b0000;

							r_next_state <= idle;									// assign next state as idle till reset not low
							//r_state_no <= 2'b0;
						end
				

			vote: if (i_voting_over == 1'b1)									// check if voting is over
						begin
							r_next_state <= finish;								// if over is high go to finish state
							//r_state_no <= 2'b11;
						end
												// if over is low contiue counting
					else if (i_candidate_1 == 1'b0 && r_cand1_prev == 1'b1)         // check falling edge of input candidate1 so only single input is regeistered 
						begin
							r_counter_1 <= r_counter_1 + 1'b1;								// increment counter for candidate 1
							//r_counter_2 <= r_counter_2;									// keep previous value of counter 
							//r_counter_3 <= r_counter_3;									// keep previous value of counter

							r_next_state <= hold;									// got to hold state
							//r_state_no <= 2'b10;
						end

					else if (i_candidate_2 == 1'b0 && r_cand2_prev == 1'b1) 		// check falling edge of input candidate2 so only single input is regeistered
						begin
							//r_counter_1 <= r_counter_1;									// keep previous value of counter 
							r_counter_2 <= r_counter_2 + 1'b1;								// increment counter for candidate 2
							//r_counter_3 <= r_counter_3;									// keep previous value of counter 

							r_next_state <= hold;									// got to hold state
							//r_state_no <= 2'b10;
						end

					else if (i_candidate_3 == 1'b0 && r_cand3_prev == 1'b1) 		// check falling edge of input candidate3 so only single input is regeistered
						begin
							//r_counter_1 <= r_counter_1;									// keep previous value of counter
							//r_counter_2 <= r_counter_2;									// keep previous value of counter
							r_counter_3 <= r_counter_3 + 1'b1;								// increment counter for candidate 3

							r_next_state <= hold;									// got to hold state
							//r_state_no <= 2'b10;
						end
					else															// none of the input present or more than 1 input present at same time
						begin
							r_counter_1 <= r_counter_1;									// keep previous value of counter
							r_counter_2 <= r_counter_2;									
							r_counter_3 <= r_counter_3;

							r_next_state <= vote;
							//r_state_no <= 2'b01;
						end

			hold: if (i_voting_over == 1'b1)									// check if over input is high
						begin
							r_next_state <= finish;									// go to finish state
							//r_state_no <= 2'b11;
						end

					else 
						begin
							if (r_hold_count != 4'b1111) begin
								r_hold_count = r_hold_count + 1'b1;
							end
							else begin
							    r_next_state <= vote;									// if over is low go to vote state
							end
							//r_state_no <= 2'b01;
						end

			finish: if (i_voting_over == 1'b0)										
						begin
							r_next_state <= idle;									// if over is low go to idle state
							//r_state_no <= 2'b0;
						end

					else
						begin
							r_next_state <= finish;									// remain in finish state if over is high
							//r_state_no <= 2'b11;
						end

			default: 
				begin 
					r_counter_1 <= 32'b0;											// default values for resgisters
					r_counter_2 <= 32'b0;
					r_counter_3 <= 32'b0;
					r_hold_count <= 4'b0000;

					r_next_state <= idle;										// by default go to idle state at the begining
					//r_state_no <= 2'b0;
				end
		endcase
	end	  

////////////// always block that performs assignment of regsiters and output on clock signal //////////////////////////////
always @(posedge clk or negedge rst)													// work on positive edge of clock 
	begin				

      if (rst == 1'b1)
			begin
				 r_present_state <= idle;											// remain in idle state when reset is high
													
				 o_count1 <= 32'b0; 												// reset final output count  
				 o_count2 <= 32'b0;
				 o_count3 <= 32'b0;
				 r_hold_count <= 4'b0000;
			end 
			
		else if (rst == 1'b0 && i_voting_over == 1'b1)											// if voting process is i.e.over is high
			begin
				 o_count1 <= r_counter_1; 											// provide value of counting registers at output
				 o_count2 <= r_counter_2;
				 o_count3 <= r_counter_3;
			end
		
		else
			begin
				r_present_state <= r_next_state;									// if reset is low keep assigning next state to present state
				r_cand1_prev <= i_candidate_1;									// keep assigning input of candidate 1 to internal register
				r_cand2_prev <= i_candidate_2;
				r_cand3_prev <= i_candidate_3;
			end
	
	end	

endmodule

voting machine/testbench.sv
//voting machine 
//Pranesh S
//VIT UNIVERSITY , VELLORE
//file name : tb_voting_machine

module tb_voting_machine ();
reg t_clk;
reg t_rst;
reg t_candidate_1;
reg t_candidate_2;
reg t_candidate_3;
reg t_vote_over;

wire [5:0] t_result_1;
wire [5:0] t_result_2;
wire [5:0] t_result_3;

//instansiate component unit under test
voting_machine uut ( 
.clk(t_clk), 
.rst(t_rst), 
.i_candidate_1(t_candidate_1), 
.i_candidate_2(t_candidate_2), 
.i_candidate_3(t_candidate_3), 
.i_voting_over(t_vote_over),
.o_count1(t_result_1),
.o_count2(t_result_2),
.o_count3(t_result_3)
);

//initial value of clock at 0 time
initial t_clk = 1'b1;

// clock generation
always
begin
    #5 t_clk = ~ t_clk;     
end

//stimulus to design
initial
begin
    $monitor ("time = %d, rst = %b, candidate_1 = %b, candidate_2 = %b, candidate_3 = %b, vote_over = %b, result_1 = %3d, result_2 = %3d, result_3 = %3d,\n",
    $time, t_rst, t_candidate_1, t_candidate_2, t_candidate_3, t_vote_over, t_result_1, t_result_2, t_result_3,);

    
    t_rst = 1'b1;
    t_candidate_1 = 1'b0;
    t_candidate_2 = 1'b0;
    t_candidate_3 = 1'b0;
    t_vote_over = 1'b0;

    #20 t_rst = 1'b0;
    #10 t_candidate_1 = 1'b1;              //when button for candidate 1 is pressed
    #10 t_candidate_1 = 1'b0;              //button  for candidate 1 is released

    #20 t_candidate_2 = 1'b1;              //when button for candidate 2 is pressed
    #10 t_candidate_2 = 1'b0;              //button  for candidate 2 is released

    #20 t_candidate_1 = 1'b1;              //when button for candidate 1 is pressed
    #10 t_candidate_1 = 1'b0;              //button  for candidate 1 is released

    #20 t_candidate_3 = 1'b1;               //when button for candidate 3 is pressed
    #10 t_candidate_3 = 1'b0;               //button  for candidate 3 is released
  
    #20 t_candidate_2 = 1'b1;
    #10 t_candidate_2 = 1'b0;

    #20 t_candidate_2 = 1'b1;
    #10 t_candidate_2 = 1'b0;
    
    #20 t_candidate_1 = 1'b1;
    #10 t_candidate_1 = 1'b0;
    
    #20 t_candidate_3 = 1'b1;               //when button for candidate 3 is pressed
    #10 t_candidate_3 = 1'b0;               //button  for candidate 3 is released


    #30 t_vote_over = 1'b1;

    #50 t_rst = 1'b1;                                    //reset when the voting process is over 
    
    //use $finish for simulators other than modelsim
    #60 $stop;                                          // use $stop instead of $finish to keep modelsim simulator open 
end

//.vcd file for gtk wave plot
initial
begin
    $dumpfile ("voting_dumpfile.vcd");
    $dumpvars (0, tb_voting_machine);
end


endmodule

voting machine/voting_dumpfile.vcd
$date
Wed Jun 25 09:27:06 2025
$end
$version
Riviera-PRO Version 2023.04.112.8911
$end
$timescale
1 ns
$end

$scope module tb_voting_machine $end
$var wire 6 ! t_result_1 [5:0] $end
$var wire 6 " t_result_2 [5:0] $end
$var wire 6 # t_result_3 [5:0] $end
$var reg 1 $ t_clk $end
$var reg 1 % t_rst $end
$var reg 1 & t_candidate_1 $end
$var reg 1 ' t_candidate_2 $end
$var reg 1 ( t_candidate_3 $end
$var reg 1 ) t_vote_over $end

$scope module uut $end
$var wire 1 * clk $end
$var wire 1 + rst $end
$var wire 1 , i_candidate_1 $end
$var wire 1 - i_candidate_2 $end
$var wire 1 . i_candidate_3 $end
$var wire 1 / i_voting_over $end
$var reg 32 0 o_count1 [31:0] $end
$var reg 32 1 o_count2 [31:0] $end
$var reg 32 2 o_count3 [31:0] $end
$var reg 32 3 r_cand1_prev [31:0] $end
$var reg 32 4 r_cand2_prev [31:0] $end
$var reg 32 5 r_cand3_prev [31:0] $end
$var reg 32 6 r_counter_1 [31:0] $end
$var reg 32 7 r_counter_2 [31:0] $end
$var reg 32 8 r_counter_3 [31:0] $end
$var reg 2 9 r_present_state [1:0] $end
$var reg 2 : r_next_state [1:0] $end
$var reg 4 ; r_hold_count [3:0] $end
$var parameter 2 < idle [1:0] $end
$var parameter 2 = vote [1:0] $end
$var parameter 2 > hold [1:0] $end
$var parameter 2 ? finish [1:0] $end
$upscope $end

$upscope $end

$enddefinitions $end
$dumpvars
b0 !
b0 "
b0 #
1$
1%
0&
0'
0(
0)
1*
1+
0,
0-
0.
0/
b0 0
b0 1
b0 2
bx 3
bx 4
bx 5
b0 6
b0 7
b0 8
b0 9
b0 :
b0 ;
b0 <
b1 =
b10 >
b11 ?
$end
#5
0$
0*
#10
1$
1*
#15
0$
0*
#20
0%
1$
1*
0+
b1 :
b0 3
b0 4
b0 5
#25
0$
0*
#30
1&
1$
1*
1,
b1 9
b1 3
#35
0$
0*
#40
0&
1$
1*
0,
b1 6
b10 :
b0 3
#45
0$
0*
#50
1$
1*
b1 :
b10 9
#55
0$
0*
#60
1'
1$
1*
1-
b1 ;
b1 9
b1 4
#65
0$
0*
#70
0'
1$
1*
0-
b1 7
b10 :
b0 4
#75
0$
0*
#80
1$
1*
b1 :
b10 9
#85
0$
0*
#90
1&
1$
1*
1,
b10 ;
b1 9
b1 3
#95
0$
0*
#100
0&
1$
1*
0,
b10 6
b10 :
b0 3
#105
0$
0*
#110
1$
1*
b1 :
b10 9
#115
0$
0*
#120
1(
1$
1*
1.
b11 ;
b1 9
b1 5
#125
0$
0*
#130
0(
1$
1*
0.
b1 8
b10 :
b0 5
#135
0$
0*
#140
1$
1*
b1 :
b10 9
#145
0$
0*
#150
1'
1$
1*
1-
b100 ;
b1 9
b1 4
#155
0$
0*
#160
0'
1$
1*
0-
b10 7
b10 :
b0 4
#165
0$
0*
#170
1$
1*
b1 :
b10 9
#175
0$
0*
#180
1'
1$
1*
1-
b101 ;
b1 9
b1 4
#185
0$
0*
#190
0'
1$
1*
0-
b11 7
b10 :
b0 4
#195
0$
0*
#200
1$
1*
b1 :
b10 9
#205
0$
0*
#210
1&
1$
1*
1,
b110 ;
b1 9
b1 3
#215
0$
0*
#220
0&
1$
1*
0,
b11 6
b10 :
b0 3
#225
0$
0*
#230
1$
1*
b1 :
b10 9
#235
0$
0*
#240
1(
1$
1*
1.
b111 ;
b1 9
b1 5
#245
0$
0*
#250
0(
1$
1*
0.
b10 8
b10 :
b0 5
#255
0$
0*
#260
1$
1*
b1 :
b10 9
#265
0$
0*
#270
1$
1*
b1000 ;
b1 9
#275
0$
0*
#280
1)
1$
1*
1/
b11 :
b11 0
b11 1
b10 2
b10 #
b11 "
b11 !
#285
0$
0*
#290
1$
1*
#295
0$
0*
#300
1$
1*
#305
0$
0*
#310
1$
1*
#315
0$
0*
#320
1$
1*
#325
0$
0*
#330
1%
1$
1*
1+
b0 9
b0 0
b0 1
b0 2
b0 ;
b0 #
b0 "
b0 !
#335
0$
0*
#340
1$
1*
b0 6
b0 7
b0 8
b0 :
