Johnson_counter/design.sv
//Pranesh S
//Johnson counter


module johnson_counter (
    input clk,
    input reset,
    output reg [3:0] q
);

always @(posedge clk or posedge reset) begin
    if (reset)
        q <= 4'b0000;  // Reset all bits to 0
    else
        q <= {~q[0], q[3:1]};  // Shift right and complement q[0]
end

endmodule

Johnson_counter/testbench.sv
//Pranesh S
//Johnson counter

module tb_johnson_counter;

reg clk;
reg reset;
wire [3:0] q;

johnson_counter uut (
    .clk(clk),
    .reset(reset),
    .q(q)
);

// Clock generation
initial begin
    clk = 0;
    forever #5 clk = ~clk;  // 10-unit period
end

// Stimulus
initial begin
    reset = 1; #10;
    reset = 0;

    #100;
    $finish;
end

// Display output in terminal
initial begin
    $monitor("Time=%0t | q=%b", $time, q);
end

// Dumpfile for GTKWave
initial begin
    $dumpfile("johnson_counter.vcd"); // Name of the VCD file
    $dumpvars(0, tb_johnson_counter); // Dump all signals in this testbench
end

endmodule

Johnson_counter/johnson_counter.vcd
$date
Thu Jun 26 11:07:38 2025
$end
$version
Riviera-PRO Version 2023.04.112.8911
$end
$timescale
1 ns
$end

$scope module tb_johnson_counter $end
$var wire 4 ! q [3:0] $end
$var reg 1 " clk $end
$var reg 1 # reset $end

$scope module uut $end
$var wire 1 $ clk $end
$var wire 1 % reset $end
$var reg 4 & q [3:0] $end
$upscope $end

$upscope $end

$enddefinitions $end
$dumpvars
b0 !
0"
1#
0$
1%
b0 &
$end
#5
1"
1$
#10
0#
0"
0$
0%
#15
1"
1$
b1000 &
b1000 !
#20
0"
0$
#25
1"
1$
b1100 &
b1100 !
#30
0"
0$
#35
1"
1$
b1110 &
b1110 !
#40
0"
0$
#45
1"
1$
b1111 &
b1111 !
#50
0"
0$
#55
1"
1$
b111 &
b111 !
#60
0"
0$
#65
1"
1$
b11 &
b11 !
#70
0"
0$
#75
1"
1$
b1 &
b1 !
#80
0"
0$
#85
1"
1$
b0 &
b0 !
#90
0"
0$
#95
1"
1$
b1000 &
b1000 !
#100
0"
0$
#105
1"
1$
b1100 &
b1100 !
